[
    {
        "from": "Traveller",
        "to": ["8A73B5", "a"],
        "title": "Do not Open",
        "body": "Lorem ipsum dolor sit amet, consectetur adipiscing elit, sed do eiusmod tempor incididunt ut labore et dolore magna aliqua.  Ut enim ad minim veniam, quis nostrud exercitation ullamco laboris nisi ut aliquip ex ea commodo consequat."
    },
    {
        "from": "Software",
        "to": ["8A73B5", "a"],
        "title": "undefined",
        "body": "001100101 011000101 0110 10 01001 01 01110 1001010101"
    },
    {
        "from": "Su'al altha",
        "to": ["Jstone"],
        "title": "Expiriments with subject 13",
        "body": "Things seem to be going unusually well with subject 13. Perhaphs they are from better stock than the usual cattle. Please keep administering serum 6 on a biweekly basis. As always I will observe the results when I am able. oh please do remember to feed and water the other human they shall be required for our next round of trials."
    },
    {
        "from": "Josephus A. Miller",
        "to": ["8A73B5", "a"],
        "title": "Contrato n22",
        "body": "Sector: X11.  Objective: Investigate the sewers and report only to me.  Reward: 22 MCr."
    },
    {
        "from": "Mike",
        "to": ["admin"],
        "title": "wtf are you kidding me?",
        "body": "Are you kidding me? Why don't you change your password?  The system is entirely compromised until you correct it.  You're the sysadmin, if you're this dumb the corporation is at risk."
    }
]
